smolagentsUI/SQL/sqlite_table_def.sql
smolagentsUI/__init__.py
smolagentsUI/agent_wrapper.py
smolagentsUI/conversation_manager.py
smolagentsUI/server.py
smolagentsUI/static/app.js
smolagentsUI/static/style.css
smolagentsUI/templates/index.html
smolagentsUI/utils.py
smolagentsui-0.1.4.dist-info/METADATA
smolagentsui-0.1.4.dist-info/WHEEL
smolagentsui-0.1.4.dist-info/RECORD
