Metadata-Version: 2.1
Name: smolagentsUI
Version: 0.1.4
Summary: A lightweight UI for smolagents
License: MIT
Author: Enshuo (David) Hsu
Requires-Python: >=3.11,<4.0
Classifier: License :: OSI Approved :: MIT License
Classifier: Programming Language :: Python :: 3
Classifier: Programming Language :: Python :: 3.11
Classifier: Programming Language :: Python :: 3.12
Requires-Dist: dill (>=0.3.7,<0.4.0)
Requires-Dist: flask (>=3.0.0,<4.0.0)
Requires-Dist: flask-socketio (>=5.3.0,<6.0.0)
Requires-Dist: simple-websocket (>=0.10.0,<0.11.0)
Requires-Dist: smolagents (>=1.23.0,<2.0.0)
